rachord/__init__.py
rachord/py.typed
rachord-0.2.0.dist-info/METADATA
rachord-0.2.0.dist-info/WHEEL
rachord-0.2.0.dist-info/licenses/LICENSE
rachord-0.2.0.dist-info/RECORD
