Metadata-Version: 2.4
Name: rachord
Version: 0.2.0
Summary: A library for plotting chord diagrams.
Project-URL: Homepage, https://gitlab.com/ratio-case-os/python/rachord
Project-URL: Bug Tracker, https://gitlab.com/ratio-case-os/python/rachord/-/issues
Author-email: "Ratio Innovations B.V." <info@ratio-case.nl>, Kenny Pang <pangkhangee@gmail.com>
License-Expression: GPL-3.0-or-later
License-File: LICENSE
Keywords: Jupyter,data science,graph,network,plot
Classifier: License :: OSI Approved :: GNU General Public License v3 (GPLv3)
Classifier: Operating System :: OS Independent
Classifier: Programming Language :: Python :: 3
Requires-Python: >=3.11
Requires-Dist: drawsvg~=2.0
Requires-Dist: numpy~=2.2
